setup.cfg
setup.py
./__init__.py
./product.py
./product.xml
./sale.py
./sale.xml
./sale_return.py
./sale_return.xml
./tryton.cfg
./tests/__init__.py
./tests/test_sale_return.py
./tests/test_views_depends.py
./view/product_category_form.xml
./view/product_template_form.xml
./view/return_policy_form.xml
./view/return_policy_term_form.xml
./view/return_policy_term_tree.xml
./view/return_policy_tree.xml
./view/return_reason_form.xml
./view/return_reason_tree.xml
./view/sale_configuration_form.xml
./view/sale_line_form.xml
fio_sale_return.egg-info/PKG-INFO
fio_sale_return.egg-info/SOURCES.txt
fio_sale_return.egg-info/dependency_links.txt
fio_sale_return.egg-info/entry_points.txt
fio_sale_return.egg-info/not-zip-safe
fio_sale_return.egg-info/requires.txt
fio_sale_return.egg-info/top_level.txt